trans.sv
enum{ADDR_SIZE = 5} as;
enum{DATA1_BUS_SIZE = 16} bds;
enum{CTR1_BUS_SIZE = 4} cbs;
enum{CACHE_SIZE = 1024} cs;
enum{CACHE_LINE_SIZE = 32} cls;
enum{C1_NOP, C1_READ8, C1_READ16, C1_READ32, C1_INVALIDATE_LINE, C1_WRITE8, C1_WRITE16, C1_WRITE32} cmd;
enum{C1_RESPONSE = 1} cache2cpu; 


module trans;
    wire[ADDR_SIZE-1:0] a1;
    wire[DATA1_BUS_SIZE-1:0] d1;
    wire[CTR1_BUS_SIZE-1:0] c1;
    reg clk;
    a cpu(a1, d1, c1, clk);
    b mem(a1, d1, c1, clk);
    initial begin 
        $dumpfile("dump_trans.vcd");
        $dumpvars(1, cpu);
        $dumpvars(1, mem);
        clk = 0;
        #20;
        $finish;
    end
    always #1 clk = ~clk;
endmodule

module a(a1, d1, c1, clk);
    output[ADDR_SIZE-1:0] a1;
    inout[DATA1_BUS_SIZE-1:0] d1;
    inout[CTR1_BUS_SIZE-1:0] c1;
    input clk;
    reg[ADDR_SIZE-1:0] a1out;
    reg[DATA1_BUS_SIZE-1:0] d1out;
    reg[CTR1_BUS_SIZE-1:0] c1out;
    reg write;
    assign d1 = write ? d1out : 8'bZ;
    assign c1 = write ? c1out : 8'bZ;
    assign a1 = a1out;
    
    initial begin
        write = 1;
        @(posedge clk);
        $display("A: send request");
        a1out = 0;
        c1out = C1_READ8;
        @(posedge clk);
        write = 0;
        @(negedge clk);
        $display("A: got answer: w %b", d1);
    end
endmodule
//lala

module b(a1, d1, c1, clk);
    input[ADDR_SIZE-1:0] a1;
    inout[DATA1_BUS_SIZE-1:0] d1;
    inout[CTR1_BUS_SIZE-1:0] c1;
    input clk;
    int adr;
    reg[DATA1_BUS_SIZE-1:0] d1out;
    reg[CTR1_BUS_SIZE-1:0] c1out;
    reg[CACHE_SIZE*8-1:0] mem;
    reg write;
    assign d1 = write ? d1out : 8'bZ;
    assign c1 = write ? c1out : 8'bZ;
    integer i = 0;
    
    initial begin
        write = 0;
        mem = 0;
        for (i = 0; i < CACHE_SIZE*8; i++) begin
            mem[i] = 1;
        end
        while (1) begin
            @(posedge clk);
            @(negedge clk);
            write = 0;
            $display("B(cache): listening request");
            case (c1)
                C1_NOP : $display("B(cache): doing nothing");
                C1_READ8 : begin
                    adr = a1;
                    @(posedge clk);
                    write = 1;
                    
                    d1out = mem[adr*8 +: 8];
                    c1out = C1_RESPONSE;
                    $display("B(cache): i want return %b", mem[adr*8 +: 8]);
                end
                default : $display("B(cache): doing default nothing");
            endcase
        end
        @(posedge clk);
    end
endmodule

dump_trans.vcd
$date
	Mon Nov 28 15:45:42 2022
$end
$version
	Icarus Verilog
$end
$timescale
	1s
$end
$scope module trans $end
$scope module cpu $end
$var wire 5 ! a1 [4:0] $end
$var wire 4 " c1 [3:0] $end
$var wire 1 # clk $end
$var wire 16 $ d1 [15:0] $end
$var reg 5 % a1out [4:0] $end
$var reg 4 & c1out [3:0] $end
$var reg 16 ' d1out [15:0] $end
$var reg 1 ( write $end
$upscope $end
$upscope $end
$scope module trans $end
$scope module mem $end
$var wire 5 ) a1 [4:0] $end
$var wire 4 * c1 [3:0] $end
$var wire 1 # clk $end
$var wire 16 + d1 [15:0] $end
$var reg 4 , c1out [3:0] $end
$var reg 16 - d1out [15:0] $end
$var reg 8192 . mem [8191:0] $end
$var reg 1 / write $end
$var integer 32 0 adr [31:0] $end
$var integer 32 1 i [31:0] $end
$upscope $end
$upscope $end
$enddefinitions $end
$comment Show the parameter values. $end
$dumpall
$end
#0
$dumpvars
b10000000000000 1
b0 0
0/
b11111111111111111111111111111111111111111111111111111111111111111111111111111111111111111111111111111111111111111111111111111111111111111111111111111111111111111111111111111111111111111111111111111111111111111111111111111111111111111111111111111111111111111111111111111111111111111111111111111111111111111111111111111111111111111111111111111111111111111111111111111111111111111111111111111111111111111111111111111111111111111111111111111111111111111111111111111111111111111111111111111111111111111111111111111111111111111111111111111111111111111111111111111111111111111111111111111111111111111111111111111111111111111111111111111111111111111111111111111111111111111111111111111111111111111111111111111111111111111111111111111111111111111111111111111111111111111111111111111111111111111111111111111111111111111111111111111111111111111111111111111111111111111111111111111111111111111111111111111111111111111111111111111111111111111111111111111111111111111111111111111111111111111111111111111111111111111111111111111111111111111111111111111111111111111111111111111111111111111111111111111111111111111111111111111111111111111111111111111111111111111111111111111111111111111111111111111111111111111111111111111111111111111111111111111111111111111111111111111111111111111111111111111111111111111111111111111111111111111111111111111111111111111111111111111111111111111111111111111111111111111111111111111111111111111111111111111111111111111111111111111111111111111111111111111111111111111111111111111111111111111111111111111111111111111111111111111111111111111111111111111111111111111111111111111111111111111111111111111111111111111111111111111111111111111111111111111111111111111111111111111111111111111111111111111111111111111111111111111111111111111111111111111111111111111111111111111111111111111111111111111111111111111111111111111111111111111111111111111111111111111111111111111111111111111111111111111111111111111111111111111111111111111111111111111111111111111111111111111111111111111111111111111111111111111111111111111111111111111111111111111111111111111111111111111111111111111111111111111111111111111111111111111111111111111111111111111111111111111111111111111111111111111111111111111111111111111111111111111111111111111111111111111111111111111111111111111111111111111111111111111111111111111111111111111111111111111111111111111111111111111111111111111111111111111111111111111111111111111111111111111111111111111111111111111111111111111111111111111111111111111111111111111111111111111111111111111111111111111111111111111111111111111111111111111111111111111111111111111111111111111111111111111111111111111111111111111111111111111111111111111111111111111111111111111111111111111111111111111111111111111111111111111111111111111111111111111111111111111111111111111111111111111111111111111111111111111111111111111111111111111111111111111111111111111111111111111111111111111111111111111111111111111111111111111111111111111111111111111111111111111111111111111111111111111111111111111111111111111111111111111111111111111111111111111111111111111111111111111111111111111111111111111111111111111111111111111111111111111111111111111111111111111111111111111111111111111111111111111111111111111111111111111111111111111111111111111111111111111111111111111111111111111111111111111111111111111111111111111111111111111111111111111111111111111111111111111111111111111111111111111111111111111111111111111111111111111111111111111111111111111111111111111111111111111111111111111111111111111111111111111111111111111111111111111111111111111111111111111111111111111111111111111111111111111111111111111111111111111111111111111111111111111111111111111111111111111111111111111111111111111111111111111111111111111111111111111111111111111111111111111111111111111111111111111111111111111111111111111111111111111111111111111111111111111111111111111111111111111111111111111111111111111111111111111111111111111111111111111111111111111111111111111111111111111111111111111111111111111111111111111111111111111111111111111111111111111111111111111111111111111111111111111111111111111111111111111111111111111111111111111111111111111111111111111111111111111111111111111111111111111111111111111111111111111111111111111111111111111111111111111111111111111111111111111111111111111111111111111111111111111111111111111111111111111111111111111111111111111111111111111111111111111111111111111111111111111111111111111111111111111111111111111111111111111111111111111111111111111111111111111111111111111111111111111111111111111111111111111111111111111111111111111111111111111111111111111111111111111111111111111111111111111111111111111111111111111111111111111111111111111111111111111111111111111111111111111111111111111111111111111111111111111111111111111111111111111111111111111111111111111111111111111111111111111111111111111111111111111111111111111111111111111111111111111111111111111111111111111111111111111111111111111111111111111111111111111111111111111111111111111111111111111111111111111111111111111111111111111111111111111111111111111111111111111111111111111111111111111111111111111111111111111111111111111111111111111111111111111111111111111111111111111111111111111111111111111111111111111111111111111111111111111111111111111111111111111111111111111111111111111111111111111111111111111111111111111111111111111111111111111111111111111111111111111111111111111111111111111111111111111111111111111111111111111111111111111111111111111111111111111111111111111111111111111111111111111111111111111111111111111111111111111111111111111111111111111111111111111111111111111111111111111111111111111111111111111111111111111111111111111111111111111111111111111111111111111111111111111111111111111111111111111111111111111111111111111111111111111111111111111111111111111111111111111111111111111111111111111111111111111111111111111111111111111111111111111111111111111111111111111111111111111111111111111111111111111111111111111111111111111111111111111111111111111111111111111111111111111111111111111111111111111111111111111111111111111111111111111111111111111111111111111111111111111111111111111111111111111111111111111111111111111111111111111111111111111111111111111111111111111111111111111111111111111111111111111111111111111111111111111111111111111111111111111111111111111111111111111111111111111111111111111111111111111111111111111111111111111111111111111111111111111111111111111111111111111111111111111111111111111111111111111111111111111111111111111111111111111111111111111111111111111111111111111111111111111111111111111111111111111111111111111111111111111111111111111111111111111111111111111111111111111111111111111111111111111111111111111111111111111111111111111111111111111111111111111111111111111111111111111111111111111111111111111111111111111111111111111111111111111111111111111111111111111111111111111111111111111111111111111111111111111111111111111111111111111111111111111111111111111111111111111111111111111111111111111111111111111111111111111111111111111111111111111111111111111111111111111111111111111111111111111111111111111111111111111111111111111111111111111111111111111111111111111111111111111111111111111111111111111111111111111111111111111111111111111111111111111111111111111111111111111111111111111111111111111111111111111111111111111111111111111111111111111111111111111111111111111111111111111111111111111111111111111111111111111111111111111111111111111111111111111111111111111111111111111111111111111111111111111111111111111111111111111111111111111111111111111111111111111111111111111111111111111111111111111111111111111111111111111111111111111111111111111111111111111111111111111111111111111111111111111111111111111111111111111111111111111111111111111111111111111111111111111111111111111111111111111111111111111111111111111111111111111111111111111111111111111111111111111111111111111111111111111111111111111111111111111111111111111111111111111111111111111111111111111111111111111111111111111111111111111111111111111111111111111111111111111111111111111111111111111111111111111111111111111111111111111111111111111111111111111111111111111111111111111111111111111111111111111111111111111111111111111111111111111111111111111111111111111111111111111111111111111111111111111111111111111111111111111111111111111111111111111111 .
bx -
bx ,
bx +
bx *
bx )
1(
bx '
bx &
bx %
bx $
0#
bx "
bx !
$end
#1
b1 "
b1 *
b1 &
b0 !
b0 )
b0 %
1#
#2
0#
#3
b11111111 $
b11111111 +
0(
b1 ,
b11111111 -
1/
1#
#4
0#
#5
1#
#6
bz "
bz *
b0zzzzzzzz $
b0zzzzzzzz +
0/
0#
#7
b1 "
b1 *
b11111111 $
b11111111 +
1/
1#
#8
0#
#9
1#
#10
bz "
bz *
b0zzzzzzzz $
b0zzzzzzzz +
0/
0#
#11
b1 "
b1 *
b11111111 $
b11111111 +
1/
1#
#12
0#
#13
1#
#14
bz "
bz *
b0zzzzzzzz $
b0zzzzzzzz +
0/
0#
#15
b1 "
b1 *
b11111111 $
b11111111 +
1/
1#
#16
0#
#17
1#
#18
bz "
bz *
b0zzzzzzzz $
b0zzzzzzzz +
0/
0#
#19
b1 "
b1 *
b11111111 $
b11111111 +
1/
1#
